{"person":{"personStatus":"Inactive","personName":"Burdell Margerum","personOnlineName":"burdell0","personFirstName":"Burdell","personLastName":"Margerum","personLegalName":"Burdell Margerum","personSortedName":"Margerum, Burdell","personInformalLetterName":"Burdell","personFormalLetterName":"Burdell Margerum","personBirthDate":"1977-03-29","personGender":"Male","personEthnicity":"Jewish","phone":[{"phoneId":"100","purpose":"Work","number":"1-627-626-2255"},{"phoneId":"110","purpose":"Home","number":"4-709-280-6867"},{"phoneId":"120","purpose":"Mobile","number":"5-821-128-4254"},{"phoneId":"130","purpose":"Mobile","number":"1-570-373-9175"},{"phoneId":"140","purpose":"Home","number":"5-338-255-2002"}],"address":[{"addressCoordinates":["-149.4672014","61.4253086"],"addressStreet":["22706 OAK KNOLL DR"],"addressLocality":"Anchorage","addressRegion":"AK","addressPostalCode":"99567","addressCountry":"United States","addressPurpose":"P.O. Box"},{"addressCoordinates":["-149.4806201","61.4253509"],"addressStreet":["22700 KNIK VISTA ST"],"addressLocality":"Anchorage","addressRegion":"AK","addressPostalCode":"99567","addressCountry":"United States","addressPurpose":"Personal"},{"addressCoordinates":["-149.4757954","61.4253268"],"addressStreet":["22700 JUDD DR"],"addressLocality":"Anchorage","addressRegion":"AK","addressPostalCode":"99567","addressCountry":"United States","addressPurpose":"Company"},{"addressCoordinates":["-149.4252291","61.4251207"],"addressStreet":["24515 GRACE ST"],"addressLocality":"Anchorage","addressRegion":"AK","addressPostalCode":"99567","addressCountry":"United States","addressPurpose":"Family"}],"email":[{"emailId":"200","purpose":"Personal","address":"burdell0@yahoo.com"},{"emailId":"210","purpose":"Company","address":"burdell0@outlook.com"},{"emailId":"220","purpose":"Personal","address":"burdell0@yahoo.com"}],"website":[{"websiteId":"600","websitePurpose":"Twitter","url":"atsm.ir"}],"customer":{"customerId":"400","status":"Active","customerJoinDate":"2009-05-17","customerReviewerRank":2},"paymentMethod":[{"paymentMethodId":"900","paymentMethodType":"Cash","paymentMethodStatus":"Active"}],"triple":[{"tripleId":"500","subject":0,"predicate":"hasSpouse","object":0},{"tripleId":"500","subject":0,"predicate":"likesProduct","object":2},{"tripleId":"500","subject":0,"predicate":"accountRepForCompany","object":0}],"metadata":{"docId":"0","docComment":"38:29. And there were offered of brass also seventy-two thousand talents, and four hundred sicles besides,","docKeywords":["8:10.","O","Lord,","our"],"schemaId":"personSchema","schemaVersion":3,"docHistory":[{"docVersion":1,"docEditorId":0,"docEvent":"Insert","docEditDateTime":"2016-05-11T18:41:16.326Z","docHistoryId":"300"},{"docVersion":1.1,"docEditorId":0,"docEvent":"Update","docEditDateTime":"2017-09-23T13:19:30.539Z","docHistoryId":"310"},{"docVersion":1.2,"docEditorId":0,"docEvent":"Update","docEditDateTime":"2018-08-29T01:52:59.902Z","docHistoryId":"320"},{"docVersion":1.3,"docEditorId":0,"docEvent":"Delete","docEditDateTime":"2018-09-07T18:50:39.315Z","docHistoryId":"330"}]}}}